{"company_id":"b7878b81-65a7-46d0-be0d-cbf8bc872379","company_name":{"value":"Acme Corp","confidence":1.0,"source":["index.html"]},"domain":{"value":"acmecorp.com","confidence":0.5,"source":["inference"]},"logo_url":{"value":"","confidence":0.0,"source":[]},"industry":{"value":"Artificial Intelligence","confidence":1.0,"source":["index.html"]},"sub_industry":{"value":"Machine Learning","confidence":0.8,"source":["index.html"]},"short_description":{"value":"We are leading the revolution in Artificial Intelligence and Machine Learning.","confidence":1.0,"source":["index.html"]},"long_description":{"value":"Founded in 2020, Acme Corp is dedicated to making AI accessible to everyone. Our team consists of world-class researchers and engineers.","confidence":1.0,"source":["index.html"]},"products_services":{"value":["AcmeAI Predictor","AcmeBot"],"confidence":1.0,"source":["index.html"]},"headquarters":{"value":"San Francisco, CA","confidence":1.0,"source":["index.html"]},"office_locations":{"value":[],"confidence":0.0,"source":[]},"key_people":{"value":[],"confidence":0.0,"source":[]},"contact_email":{"value":"","confidence":0.0,"source":[]},"contact_phone":{"value":"","confidence":0.0,"source":[]},"contact_page":{"value":"","confidence":0.0,"source":[]},"tech_stack_signals":{"value":["TensorFlow","Vue.js","Python","WordPress 6.0","Google Analytics"],"confidence":1.0,"source":["index.html"]},"founded_year":{"value":"2020","confidence":1.0,"source":["index.html"]},"missing_fields":["domain","logo_url","office_locations","key_people","contact_email","contact_phone","contact_page"],"created_at":"2025-12-17T23:54:41.311509"}